gabrielribalves_mifflin/__init__.py
gabrielribalves_mifflin/__main__.py
gabrielribalves_mifflin/cli.py
gabrielribalves_mifflin/core.py
gabrielribalves_mifflin/database.py
gabrielribalves_mifflin/settings.py
gabrielribalves_mifflin/utils/__init__.py
gabrielribalves_mifflin/utils/email.py
gabrielribalves_mifflin/utils/log.py
gabrielribalves_mifflin/utils/user.py
tests/__init__.py
tests/conftest.py
tests/constants.py
tests/test_add.py
tests/test_database.py
tests/test_load.py
tests/test_read.py
tests/test_utils.py
tests/utils.py
tests/assets/people.csv
gabrielribalves_mifflin-0.1.4.dist-info/LICENSE
gabrielribalves_mifflin-0.1.4.dist-info/METADATA
gabrielribalves_mifflin-0.1.4.dist-info/WHEEL
gabrielribalves_mifflin-0.1.4.dist-info/entry_points.txt
gabrielribalves_mifflin-0.1.4.dist-info/top_level.txt
gabrielribalves_mifflin-0.1.4.dist-info/RECORD
